odoo/addons/product_dimension_compute_volume/README.rst
odoo/addons/product_dimension_compute_volume/__init__.py
odoo/addons/product_dimension_compute_volume/__manifest__.py
odoo/addons/product_dimension_compute_volume/i18n/it.po
odoo/addons/product_dimension_compute_volume/i18n/product_dimension_compute_volume.pot
odoo/addons/product_dimension_compute_volume/models/__init__.py
odoo/addons/product_dimension_compute_volume/models/product.py
odoo/addons/product_dimension_compute_volume/readme/CONTRIBUTORS.rst
odoo/addons/product_dimension_compute_volume/readme/DESCRIPTION.rst
odoo/addons/product_dimension_compute_volume/readme/ROADMAP.rst
odoo/addons/product_dimension_compute_volume/static/description/icon.png
odoo/addons/product_dimension_compute_volume/static/description/index.html
odoo/addons/product_dimension_compute_volume/tests/__init__.py
odoo/addons/product_dimension_compute_volume/tests/test_product.py
odoo12_addon_product_dimension_compute_volume-12.0.1.0.0.99.dev10.dist-info/METADATA
odoo12_addon_product_dimension_compute_volume-12.0.1.0.0.99.dev10.dist-info/WHEEL
odoo12_addon_product_dimension_compute_volume-12.0.1.0.0.99.dev10.dist-info/top_level.txt
odoo12_addon_product_dimension_compute_volume-12.0.1.0.0.99.dev10.dist-info/RECORD
